[
  {
    "_id": "97109780-a2a5-11e7-928f-5dbe6f6f5519",
    "_type": "visualization",
    "_source": {
      "title": "Dashboards [Filebeat Nginx]",
      "visState": "{\"title\":\"Dashboards [Filebeat Nginx]\",\"type\":\"markdown\",\"params\":{\"markdown\":\"[Nginx logs overview](#/dashboard/55a9e6e0-a29e-11e7-928f-5dbe6f6f5519) | [Nginx access and error logs](#/dashboard/046212a0-a2a1-11e7-928f-5dbe6f6f5519)\\n\\n[PEP Dashboard](#/dashboard/a9846f70-876b-11e9-ae20-e9048aafefb0)\",\"fontSize\":12,\"openLinksInNewTab\":false},\"aggs\":[]}",
      "uiStateJSON": "{}",
      "description": "",
      "version": 1,
      "kibanaSavedObjectMeta": {
        "searchSourceJSON": "{\"query\":{\"query\":\"\",\"language\":\"kuery\"},\"filter\":[]}"
      }
    },
    "_migrationVersion": {
      "visualization": "7.0.0"
    },
    "_references": []
  },
  {
    "_id": "4659cbc0-8144-11e9-81cc-9f93c9652c02",
    "_type": "visualization",
    "_source": {
      "title": "Instance selector [Kheops]",
      "visState": "{\"title\":\"Instance selector [Kheops]\",\"type\":\"input_control_vis\",\"params\":{\"controls\":[{\"id\":\"1559046528292\",\"fieldName\":\"fields.instance.keyword\",\"parent\":\"\",\"label\":\"Instance selector\",\"type\":\"list\",\"options\":{\"type\":\"terms\",\"multiselect\":false,\"dynamicOptions\":true,\"size\":5,\"order\":\"desc\"},\"indexPatternRefName\":\"control_0_index_pattern\"},{\"id\":\"1559637621552\",\"fieldName\":\"beat.name.keyword\",\"parent\":\"1559046528292\",\"label\":\"Nginx selector\",\"type\":\"list\",\"options\":{\"type\":\"terms\",\"multiselect\":false,\"dynamicOptions\":true,\"size\":5,\"order\":\"desc\"},\"indexPatternRefName\":\"control_1_index_pattern\"}],\"updateFiltersOnChange\":true,\"useTimeFilter\":true,\"pinFilters\":true},\"aggs\":[]}",
      "uiStateJSON": "{}",
      "description": "",
      "version": 1,
      "kibanaSavedObjectMeta": {
        "searchSourceJSON": "{\"query\":{\"query\":\"\",\"language\":\"kuery\"},\"filter\":[]}"
      }
    },
    "_migrationVersion": {
      "visualization": "7.0.0"
    },
    "_references": [
      {
        "name": "control_0_index_pattern",
        "type": "index-pattern",
        "id": "677aef70-8601-11e9-808b-2d2bf6b1f0ee"
      },
      {
        "name": "control_1_index_pattern",
        "type": "index-pattern",
        "id": "677aef70-8601-11e9-808b-2d2bf6b1f0ee"
      }
    ]
  },
  {
    "_id": "173ba0e0-807a-11e9-88a1-99a36760182c",
    "_type": "visualization",
    "_source": {
      "title": "Nginx Top Country",
      "visState": "{\"title\":\"Nginx Top Country\",\"type\":\"tagcloud\",\"params\":{\"scale\":\"log\",\"orientation\":\"right angled\",\"minFontSize\":18,\"maxFontSize\":50,\"showLabel\":false},\"aggs\":[{\"id\":\"1\",\"enabled\":true,\"type\":\"count\",\"schema\":\"metric\",\"params\":{}},{\"id\":\"2\",\"enabled\":true,\"type\":\"terms\",\"schema\":\"segment\",\"params\":{\"field\":\"geoip.country_name.keyword\",\"size\":10,\"order\":\"desc\",\"orderBy\":\"1\",\"otherBucket\":false,\"otherBucketLabel\":\"Other\",\"missingBucket\":false,\"missingBucketLabel\":\"Missing\"}}]}",
      "uiStateJSON": "{}",
      "description": "",
      "version": 1,
      "kibanaSavedObjectMeta": {
        "searchSourceJSON": "{\"query\":{\"query\":\"\",\"language\":\"lucene\"},\"filter\":[],\"indexRefName\":\"kibanaSavedObjectMeta.searchSourceJSON.index\"}"
      }
    },
    "_migrationVersion": {
      "visualization": "7.0.0"
    },
    "_references": [
      {
        "name": "kibanaSavedObjectMeta.searchSourceJSON.index",
        "type": "index-pattern",
        "id": "677aef70-8601-11e9-808b-2d2bf6b1f0ee"
      }
    ]
  },
  {
    "_id": "c3299070-8079-11e9-88a1-99a36760182c",
    "_type": "visualization",
    "_source": {
      "title": "Nginx Map [Filebeat]",
      "visState": "{\n  \"title\": \"Nginx Map [Filebeat]\",\n  \"type\": \"tile_map\",\n  \"params\": {\n    \"colorSchema\": \"Yellow to Red\",\n    \"mapType\": \"Scaled Circle Markers\",\n    \"isDesaturated\": true,\n    \"addTooltip\": true,\n    \"heatClusterSize\": 1.5,\n    \"legendPosition\": \"bottomright\",\n    \"mapZoom\": 2,\n    \"mapCenter\": [\n      0,\n      0\n    ],\n    \"wms\": {\n      \"enabled\": false,\n      \"options\": {\n        \"format\": \"image/png\",\n        \"transparent\": true\n      },\n      \"selectedTmsLayer\": {\n        \"origin\": \"elastic_maps_service\",\n        \"id\": \"road_map\",\n        \"minZoom\": 0,\n        \"maxZoom\": 18,\n        \"attribution\": \"<p>&#169; <a href=\\\"https://www.openstreetmap.org/copyright\\\">OpenStreetMap contributors</a>|<a href=\\\"https://openmaptiles.org\\\">OpenMapTiles</a>|<a href=\\\"https://www.maptiler.com\\\">MapTiler</a>|<a href=\\\"https://www.elastic.co/elastic-maps-service\\\">Elastic Maps Service</a></p>&#10;\"\n      }\n    }\n  },\n  \"aggs\": [\n    {\n      \"id\": \"1\",\n      \"enabled\": true,\n      \"type\": \"count\",\n      \"schema\": \"metric\",\n      \"params\": {}\n    },\n    {\n      \"id\": \"2\",\n      \"enabled\": true,\n      \"type\": \"geohash_grid\",\n      \"schema\": \"segment\",\n      \"params\": {\n        \"field\": \"geoip.location\",\n        \"autoPrecision\": true,\n        \"isFilteredByCollar\": true,\n        \"useGeocentroid\": true,\n        \"mapZoom\": 7,\n        \"mapCenter\": {\n          \"lon\": 11.09619140625,\n          \"lat\": 45.663966415824056\n        },\n        \"mapBounds\": {\n          \"bottom_right\": {\n            \"lat\": 42.24478535602799,\n            \"lon\": 19.237060546875\n          },\n          \"top_left\": {\n            \"lat\": 48.88639177703194,\n            \"lon\": 2.9553222656249987\n          }\n        },\n        \"precision\": 4\n      }\n    }\n  ]\n}",
      "uiStateJSON": "{\n  \"mapZoom\": 7,\n  \"mapCenter\": [\n    45.663966415824056,\n    11.09619140625\n  ]\n}",
      "description": "",
      "version": 1,
      "kibanaSavedObjectMeta": {
        "searchSourceJSON": "{\n  \"query\": {\n    \"query\": \"\",\n    \"language\": \"lucene\"\n  },\n  \"filter\": [],\n  \"indexRefName\": \"kibanaSavedObjectMeta.searchSourceJSON.index\"\n}"
      }
    },
    "_migrationVersion": {
      "visualization": "7.0.0"
    },
    "_references": [
      {
        "name": "kibanaSavedObjectMeta.searchSourceJSON.index",
        "id": "677aef70-8601-11e9-808b-2d2bf6b1f0ee",
        "type": "index-pattern"
      }
    ]
  },
  {
    "_id": "b70b1b20-a1f4-11e7-928f-5dbe6f6f5519",
    "_type": "visualization",
    "_source": {
      "title": "Response codes over time [Filebeat Nginx]",
      "visState": "{\"title\":\"Response codes over time [Filebeat Nginx]\",\"type\":\"metrics\",\"params\":{\"time_field\":\"@timestamp\",\"series\":[{\"line_width\":1,\"terms_field\":\"nginx.access.response_code\",\"point_size\":1,\"split_filters\":[{\"filter\":\"nginx.access.response_code:[200 TO 299]\",\"label\":\"200\",\"color\":\"#68BC00\",\"id\":\"5acdc750-a29d-11e7-a062-a1c3587f4874\"},{\"filter\":\"nginx.access.response_code:[300 TO 399]\",\"label\":\"300\",\"color\":\"rgba(252,196,0,1)\",\"id\":\"6efd2ae0-a29d-11e7-a062-a1c3587f4874\"},{\"filter\":\"nginx.access.response_code:[400 TO 499]\",\"label\":\"400\",\"color\":\"rgba(211,49,21,1)\",\"id\":\"76089a90-a29d-11e7-a062-a1c3587f4874\"},{\"filter\":\"nginx.access.response_code:[500 TO 599]\",\"label\":\"500\",\"color\":\"rgba(171,20,158,1)\",\"id\":\"7c7929d0-a29d-11e7-a062-a1c3587f4874\"}],\"color\":\"#68BC00\",\"label\":\"\",\"metrics\":[{\"type\":\"count\",\"id\":\"61ca57f2-469d-11e7-af02-69e470af7417\"}],\"seperate_axis\":0,\"split_mode\":\"filters\",\"chart_type\":\"bar\",\"terms_order_by\":\"61ca57f2-469d-11e7-af02-69e470af7417\",\"stacked\":\"stacked\",\"axis_position\":\"right\",\"formatter\":\"number\",\"id\":\"61ca57f1-469d-11e7-af02-69e470af7417\",\"fill\":0.5}],\"axis_formatter\":\"number\",\"interval\":\"auto\",\"id\":\"61ca57f0-469d-11e7-af02-69e470af7417\",\"filter\":\"\",\"show_legend\":1,\"show_grid\":1,\"legend_position\":\"bottom\",\"index_pattern\":\"kheopsnginx-*\",\"type\":\"timeseries\",\"axis_position\":\"left\",\"axis_scale\":\"normal\",\"default_index_pattern\":\"kheopsnginx-*\"},\"aggs\":[]}",
      "uiStateJSON": "{}",
      "description": "",
      "version": 1,
      "kibanaSavedObjectMeta": {
        "searchSourceJSON": "{\"query\":{\"query\":\"\",\"language\":\"kuery\"},\"filter\":[]}"
      }
    },
    "_migrationVersion": {
      "visualization": "7.0.0"
    },
    "_references": []
  },
  {
    "_id": "0d69c650-6d83-11e9-99bc-d5ddcc90f43b",
    "_type": "visualization",
    "_source": {
      "title": "Method over time [Filebeat Nginx]",
      "visState": "{\"title\":\"Method over time [Filebeat Nginx]\",\"type\":\"metrics\",\"params\":{\"time_field\":\"@timestamp\",\"series\":[{\"line_width\":\"0\",\"terms_field\":\"nginx.access.method.keyword\",\"point_size\":1,\"split_filters\":[{\"filter\":\"nginx.access.method:GET\",\"label\":\"GET\",\"color\":\"#68BC00\",\"id\":\"5acdc750-a29d-11e7-a062-a1c3587f4874\"},{\"filter\":\"nginx.access.method:POST\",\"label\":\"POST\",\"color\":\"rgba(252,196,0,1)\",\"id\":\"6efd2ae0-a29d-11e7-a062-a1c3587f4874\"},{\"filter\":\"nginx.access.method:DELETE\",\"label\":\"DELETE\",\"color\":\"rgba(211,49,21,1)\",\"id\":\"76089a90-a29d-11e7-a062-a1c3587f4874\"},{\"filter\":\"nginx.access.method:PUT\",\"label\":\"PUT\",\"color\":\"rgba(171,20,158,1)\",\"id\":\"7c7929d0-a29d-11e7-a062-a1c3587f4874\"},{\"filter\":\"nginx.access.method:OPTIONS\",\"label\":\"OPTIONS\",\"color\":\"rgba(15,20,25,1)\",\"id\":\"b51ff510-6d81-11e9-b19c-096a6388b44d\"},{\"filter\":\"nginx.access.method:PATCH\",\"label\":\"PATCH\",\"color\":\"rgba(22,165,165,1)\",\"id\":\"ca26cce0-6d81-11e9-b19c-096a6388b44d\"},{\"filter\":\"NOT nginx.access.method:GET AND NOT nginx.access.method:POST AND NOT nginx.access.method:PUT AND NOT nginx.access.method:DELETE AND NOT nginx.access.method:OPTIONS AND NOT nginx.access.method:PATCH AND nginx.access.method:*\",\"label\":\"other\",\"color\":\"rgba(250,40,255,1)\",\"id\":\"e4809980-6d82-11e9-b19c-096a6388b44d\"}],\"color\":\"#68BC00\",\"label\":\"\",\"metrics\":[{\"type\":\"count\",\"id\":\"61ca57f2-469d-11e7-af02-69e470af7417\"}],\"seperate_axis\":0,\"split_mode\":\"filters\",\"chart_type\":\"bar\",\"terms_order_by\":\"61ca57f2-469d-11e7-af02-69e470af7417\",\"stacked\":\"stacked\",\"axis_position\":\"right\",\"formatter\":\"number\",\"id\":\"61ca57f1-469d-11e7-af02-69e470af7417\",\"fill\":\"0.8\",\"terms_size\":\"20\",\"split_color_mode\":\"rainbow\",\"separate_axis\":0,\"series_drop_last_bucket\":0,\"hide_in_legend\":0,\"offset_time\":\"\",\"hidden\":false}],\"axis_formatter\":\"number\",\"interval\":\"auto\",\"id\":\"61ca57f0-469d-11e7-af02-69e470af7417\",\"filter\":\"nginx.log_type:access\",\"show_legend\":1,\"show_grid\":1,\"legend_position\":\"bottom\",\"index_pattern\":\"kheopsnginx-*\",\"type\":\"timeseries\",\"axis_position\":\"left\",\"axis_scale\":\"normal\",\"default_index_pattern\":\"kheopsnginx-*\",\"background_color\":null,\"bar_color_rules\":[{\"id\":\"eacb09b0-6daf-11e9-af25-41e700ff65f2\"}],\"annotations\":[]},\"aggs\":[]}",
      "uiStateJSON": "{}",
      "description": "",
      "version": 1,
      "kibanaSavedObjectMeta": {
        "searchSourceJSON": "{\"query\":{\"query\":\"\",\"language\":\"kuery\"},\"filter\":[]}"
      }
    },
    "_migrationVersion": {
      "visualization": "7.0.0"
    },
    "_references": []
  },
  {
    "_id": "46322e50-a1f6-11e7-928f-5dbe6f6f5519",
    "_type": "visualization",
    "_source": {
      "title": "Errors over time [Filebeat Nginx]",
      "visState": "{\"title\":\"Errors over time [Filebeat Nginx]\",\"type\":\"metrics\",\"params\":{\"time_field\":\"@timestamp\",\"series\":[{\"line_width\":1,\"terms_field\":\"nginx.error.level\",\"point_size\":1,\"color\":\"rgba(211,49,21,1)\",\"metrics\":[{\"type\":\"count\",\"id\":\"61ca57f2-469d-11e7-af02-69e470af7417\"}],\"seperate_axis\":0,\"split_mode\":\"everything\",\"chart_type\":\"bar\",\"terms_order_by\":\"61ca57f2-469d-11e7-af02-69e470af7417\",\"stacked\":\"none\",\"axis_position\":\"right\",\"formatter\":\"number\",\"id\":\"61ca57f1-469d-11e7-af02-69e470af7417\",\"fill\":0.5}],\"axis_formatter\":\"number\",\"interval\":\"auto\",\"id\":\"61ca57f0-469d-11e7-af02-69e470af7417\",\"filter\":\"nginx.log_type:error\",\"show_legend\":1,\"show_grid\":1,\"legend_position\":\"bottom\",\"index_pattern\":\"kheopsnginx-*\",\"type\":\"timeseries\",\"axis_position\":\"left\",\"axis_scale\":\"normal\",\"default_index_pattern\":\"kheopsnginx-*\"},\"aggs\":[]}",
      "uiStateJSON": "{}",
      "description": "",
      "version": 1,
      "kibanaSavedObjectMeta": {
        "searchSourceJSON": "{\"query\":{\"query\":\"\",\"language\":\"kuery\"},\"filter\":[]}"
      }
    },
    "_migrationVersion": {
      "visualization": "7.0.0"
    },
    "_references": []
  },
  {
    "_id": "0dd6f320-a29f-11e7-928f-5dbe6f6f5519",
    "_type": "visualization",
    "_source": {
      "title": "Data Volume [Filebeat Nginx]",
      "visState": "{\"title\":\"Data Volume [Filebeat Nginx]\",\"type\":\"metrics\",\"params\":{\"time_field\":\"@timestamp\",\"series\":[{\"line_width\":1,\"terms_field\":null,\"point_size\":1,\"split_filters\":[{\"color\":\"#68BC00\",\"filter\":\"nginx.access.response_code:[200 TO 299]\",\"id\":\"7c343c20-a29e-11e7-a062-a1c3587f4874\",\"label\":\"200s\"}],\"color\":\"#68BC00\",\"label\":\"\",\"metrics\":[{\"field\":\"nginx.access.body_sent.bytes\",\"type\":\"sum\",\"id\":\"61ca57f2-469d-11e7-af02-69e470af7417\"}],\"seperate_axis\":0,\"split_mode\":\"everything\",\"chart_type\":\"line\",\"stacked\":\"none\",\"axis_position\":\"right\",\"formatter\":\"number\",\"id\":\"61ca57f1-469d-11e7-af02-69e470af7417\",\"fill\":0.5,\"value_template\":\"{{value}} Bytes\"}],\"axis_formatter\":\"number\",\"interval\":\"auto\",\"id\":\"61ca57f0-469d-11e7-af02-69e470af7417\",\"filter\":\"\",\"show_legend\":1,\"show_grid\":1,\"legend_position\":\"bottom\",\"index_pattern\":\"kheopsnginx-*\",\"type\":\"timeseries\",\"axis_position\":\"left\",\"axis_scale\":\"normal\",\"default_index_pattern\":\"kheopsnginx-*\"},\"aggs\":[]}",
      "uiStateJSON": "{}",
      "description": "",
      "version": 1,
      "kibanaSavedObjectMeta": {
        "searchSourceJSON": "{\"query\":{\"language\":\"kuery\",\"query\":\"\"},\"filter\":[]}"
      }
    },
    "_migrationVersion": {
      "visualization": "7.0.0"
    },
    "_references": []
  },
  {
    "_id": "fc7c2d00-811a-11e9-81cc-9f93c9652c02",
    "_type": "visualization",
    "_source": {
      "title": "Response time [Kheops Nginx]",
      "visState": "{\n  \"aggs\": [\n    {\n      \"enabled\": true,\n      \"id\": \"1\",\n      \"params\": {\n        \"customLabel\": \"\",\n        \"field\": \"nginx.access.request_time\"\n      },\n      \"schema\": \"metric\",\n      \"type\": \"max\"\n    },\n    {\n      \"enabled\": true,\n      \"id\": \"2\",\n      \"params\": {\n        \"customInterval\": \"2h\",\n        \"drop_partials\": false,\n        \"extended_bounds\": {},\n        \"field\": \"@timestamp\",\n        \"interval\": \"auto\",\n        \"min_doc_count\": 1,\n        \"timeRange\": {\n          \"from\": \"now/d\",\n          \"to\": \"now/d\"\n        },\n        \"time_zone\": \"Europe/Zurich\",\n        \"useNormalizedEsInterval\": true\n      },\n      \"schema\": \"segment\",\n      \"type\": \"date_histogram\"\n    },\n    {\n      \"enabled\": true,\n      \"id\": \"3\",\n      \"params\": {\n        \"field\": \"nginx.access.method.keyword\",\n        \"missingBucket\": false,\n        \"missingBucketLabel\": \"Missing\",\n        \"order\": \"desc\",\n        \"orderBy\": \"1\",\n        \"otherBucket\": false,\n        \"otherBucketLabel\": \"Other\",\n        \"size\": 10\n      },\n      \"schema\": \"group\",\n      \"type\": \"terms\"\n    }\n  ],\n  \"params\": {\n    \"addLegend\": true,\n    \"addTooltip\": true,\n    \"colorSchema\": \"Green to Red\",\n    \"colorsNumber\": 4,\n    \"colorsRange\": [\n      {\n        \"from\": 0,\n        \"to\": 0.5\n      },\n      {\n        \"from\": 0.5,\n        \"to\": 2\n      },\n      {\n        \"from\": 2,\n        \"to\": 5\n      },\n      {\n        \"from\": 5,\n        \"to\": 15\n      },\n      {\n        \"from\": 15,\n        \"to\": 999\n      }\n    ],\n    \"enableHover\": true,\n    \"invertColors\": false,\n    \"legendPosition\": \"right\",\n    \"percentageMode\": false,\n    \"setColorRange\": true,\n    \"times\": [],\n    \"type\": \"heatmap\",\n    \"valueAxes\": [\n      {\n        \"id\": \"ValueAxis-1\",\n        \"labels\": {\n          \"color\": \"black\",\n          \"overwriteColor\": false,\n          \"rotate\": 0,\n          \"show\": false\n        },\n        \"scale\": {\n          \"defaultYExtents\": false,\n          \"type\": \"linear\"\n        },\n        \"show\": false,\n        \"type\": \"value\"\n      }\n    ]\n  },\n  \"title\": \"Response time [Kheops Nginx]\",\n  \"type\": \"heatmap\"\n}",
      "uiStateJSON": "{\n  \"vis\": {\n    \"colors\": {\n      \"0 - 0.5\": \"#E0F9D7\",\n      \"0.5 - 1\": \"#629E51\",\n      \"0.5 - 2\": \"#9AC48A\",\n      \"1 - 3\": \"#FCEACA\",\n      \"15 - 999\": \"#E24D42\",\n      \"2 - 5\": \"#FCE2DE\",\n      \"3 - 15\": \"#F9BA8F\",\n      \"5 - 15\": \"#F29191\"\n    },\n    \"defaultColors\": {\n      \"0 - 0.5\": \"rgb(0,104,55)\",\n      \"0.5 - 2\": \"rgb(102,189,99)\",\n      \"2 - 5\": \"rgb(217,239,139)\",\n      \"5 - 15\": \"rgb(254,224,139)\",\n      \"15 - 999\": \"rgb(244,109,67)\"\n    }\n  }\n}",
      "description": "",
      "version": 1,
      "kibanaSavedObjectMeta": {
        "searchSourceJSON": "{\n  \"query\": {\n    \"language\": \"kuery\",\n    \"query\": \"\"\n  },\n  \"filter\": [],\n  \"indexRefName\": \"kibanaSavedObjectMeta.searchSourceJSON.index\"\n}"
      }
    },
    "_migrationVersion": {
      "visualization": "7.0.0"
    },
    "_references": [
      {
        "name": "kibanaSavedObjectMeta.searchSourceJSON.index",
        "id": "677aef70-8601-11e9-808b-2d2bf6b1f0ee",
        "type": "index-pattern"
      }
    ]
  },
  {
    "_id": "e96efad0-8787-11e9-a9bc-c3a3f8efe13c",
    "_type": "visualization",
    "_source": {
      "title": "top request generic [kheops] (only api)",
      "visState": "{\"title\":\"top request generic [kheops] (only api)\",\"type\":\"horizontal_bar\",\"params\":{\"type\":\"histogram\",\"grid\":{\"categoryLines\":false},\"categoryAxes\":[{\"id\":\"CategoryAxis-1\",\"type\":\"category\",\"position\":\"left\",\"show\":true,\"style\":{},\"scale\":{\"type\":\"linear\"},\"labels\":{\"show\":true,\"rotate\":0,\"filter\":false,\"truncate\":200},\"title\":{}}],\"valueAxes\":[{\"id\":\"ValueAxis-1\",\"name\":\"LeftAxis-1\",\"type\":\"value\",\"position\":\"bottom\",\"show\":true,\"style\":{},\"scale\":{\"type\":\"linear\",\"mode\":\"normal\"},\"labels\":{\"show\":true,\"rotate\":75,\"filter\":true,\"truncate\":100},\"title\":{\"text\":\"Count\"}}],\"seriesParams\":[{\"show\":true,\"type\":\"histogram\",\"mode\":\"normal\",\"data\":{\"label\":\"Count\",\"id\":\"1\"},\"valueAxis\":\"ValueAxis-1\",\"drawLinesBetweenPoints\":true,\"showCircles\":true}],\"addTooltip\":true,\"addLegend\":true,\"legendPosition\":\"top\",\"times\":[],\"addTimeMarker\":false,\"orderBucketsBySum\":true},\"aggs\":[{\"id\":\"1\",\"enabled\":true,\"type\":\"count\",\"schema\":\"metric\",\"params\":{}},{\"id\":\"2\",\"enabled\":true,\"type\":\"terms\",\"schema\":\"segment\",\"params\":{\"field\":\"generic_url.keyword\",\"size\":60,\"order\":\"desc\",\"orderBy\":\"1\",\"otherBucket\":false,\"otherBucketLabel\":\"Other\",\"missingBucket\":false,\"missingBucketLabel\":\"Missing\",\"customLabel\":\".\"}}]}",
      "uiStateJSON": "{}",
      "description": "",
      "version": 1,
      "kibanaSavedObjectMeta": {
        "searchSourceJSON": "{\"query\":{\"query\":\"\",\"language\":\"kuery\"},\"filter\":[]}"
      },
      "savedSearchRefName": "search_0"
    },
    "_migrationVersion": {
      "visualization": "7.0.0"
    },
    "_references": [
      {
        "name": "search_0",
        "type": "search",
        "id": "626cc120-8787-11e9-a9bc-c3a3f8efe13c"
      }
    ]
  },
  {
    "_id": "1bd603a0-8798-11e9-bfec-155022556871",
    "_type": "visualization",
    "_source": {
      "title": "Top 10 album id [kheops reverse proxy]",
      "visState": "{\"title\":\"Top 10 album id [kheops reverse proxy]\",\"type\":\"horizontal_bar\",\"params\":{\"type\":\"histogram\",\"grid\":{\"categoryLines\":false},\"categoryAxes\":[{\"id\":\"CategoryAxis-1\",\"type\":\"category\",\"position\":\"left\",\"show\":true,\"style\":{},\"scale\":{\"type\":\"linear\"},\"labels\":{\"show\":true,\"rotate\":0,\"filter\":false,\"truncate\":200},\"title\":{}}],\"valueAxes\":[{\"id\":\"ValueAxis-1\",\"name\":\"LeftAxis-1\",\"type\":\"value\",\"position\":\"bottom\",\"show\":true,\"style\":{},\"scale\":{\"type\":\"linear\",\"mode\":\"normal\"},\"labels\":{\"show\":true,\"rotate\":75,\"filter\":true,\"truncate\":100},\"title\":{\"text\":\"Count\"}}],\"seriesParams\":[{\"show\":true,\"type\":\"histogram\",\"mode\":\"normal\",\"data\":{\"label\":\"Count\",\"id\":\"1\"},\"valueAxis\":\"ValueAxis-1\",\"drawLinesBetweenPoints\":true,\"showCircles\":true}],\"addTooltip\":true,\"addLegend\":true,\"legendPosition\":\"top\",\"times\":[],\"addTimeMarker\":false,\"orderBucketsBySum\":true},\"aggs\":[{\"id\":\"1\",\"enabled\":true,\"type\":\"count\",\"schema\":\"metric\",\"params\":{}},{\"id\":\"2\",\"enabled\":true,\"type\":\"terms\",\"schema\":\"segment\",\"params\":{\"field\":\"path_param.album_id.keyword\",\"size\":10,\"order\":\"desc\",\"orderBy\":\"1\",\"otherBucket\":false,\"otherBucketLabel\":\"Other\",\"missingBucket\":false,\"missingBucketLabel\":\"Missing\",\"customLabel\":\"album ID\"}}]}",
      "uiStateJSON": "{}",
      "description": "",
      "version": 1,
      "kibanaSavedObjectMeta": {
        "searchSourceJSON": "{\"query\":{\"query\":\"\",\"language\":\"kuery\"},\"filter\":[],\"indexRefName\":\"kibanaSavedObjectMeta.searchSourceJSON.index\"}"
      }
    },
    "_migrationVersion": {
      "visualization": "7.0.0"
    },
    "_references": [
      {
        "name": "kibanaSavedObjectMeta.searchSourceJSON.index",
        "type": "index-pattern",
        "id": "677aef70-8601-11e9-808b-2d2bf6b1f0ee"
      }
    ]
  },
  {
    "_id": "fb4bc980-6d75-11e9-99bc-d5ddcc90f43b",
    "_type": "visualization",
    "_source": {
      "title": "Operating systems breakdown [Filebeat Nginx]",
      "visState": "{\n  \"title\": \"Operating systems breakdown [Filebeat Nginx]\",\n  \"type\": \"pie\",\n  \"params\": {\n    \"addLegend\": true,\n    \"addTooltip\": true,\n    \"isDonut\": true,\n    \"labels\": {\n      \"last_level\": true,\n      \"show\": false,\n      \"truncate\": 100,\n      \"values\": true\n    },\n    \"legendPosition\": \"bottom\",\n    \"type\": \"pie\"\n  },\n  \"aggs\": [\n    {\n      \"id\": \"1\",\n      \"enabled\": true,\n      \"type\": \"count\",\n      \"schema\": \"metric\",\n      \"params\": {}\n    },\n    {\n      \"id\": \"3\",\n      \"enabled\": true,\n      \"type\": \"terms\",\n      \"schema\": \"segment\",\n      \"params\": {\n        \"field\": \"nginx.access.user_agent.os.keyword\",\n        \"size\": 5,\n        \"order\": \"desc\",\n        \"orderBy\": \"1\",\n        \"otherBucket\": false,\n        \"otherBucketLabel\": \"Other\",\n        \"missingBucket\": false,\n        \"missingBucketLabel\": \"Missing\"\n      }\n    },\n    {\n      \"id\": \"2\",\n      \"enabled\": true,\n      \"type\": \"terms\",\n      \"schema\": \"segment\",\n      \"params\": {\n        \"field\": \"nginx.access.user_agent.os_minor.keyword\",\n        \"size\": 5,\n        \"order\": \"desc\",\n        \"orderBy\": \"1\",\n        \"otherBucket\": false,\n        \"otherBucketLabel\": \"Other\",\n        \"missingBucket\": false,\n        \"missingBucketLabel\": \"Missing\"\n      }\n    }\n  ]\n}",
      "uiStateJSON": "{}",
      "description": "",
      "version": 1,
      "kibanaSavedObjectMeta": {
        "searchSourceJSON": "{\n  \"query\": {\n    \"query\": \"\",\n    \"language\": \"kuery\"\n  },\n  \"filter\": [],\n  \"indexRefName\": \"kibanaSavedObjectMeta.searchSourceJSON.index\"\n}"
      }
    },
    "_migrationVersion": {
      "visualization": "7.0.0"
    },
    "_references": [
      {
        "name": "kibanaSavedObjectMeta.searchSourceJSON.index",
        "id": "677aef70-8601-11e9-808b-2d2bf6b1f0ee",
        "type": "index-pattern"
      }
    ]
  },
  {
    "_id": "4196a6f0-6b62-11e9-abc4-915693593db1",
    "_type": "visualization",
    "_source": {
      "title": "Browsers breakdown [Filebeat Nginx]",
      "visState": "{\n  \"title\": \"Browsers breakdown [Filebeat Nginx]\",\n  \"type\": \"pie\",\n  \"params\": {\n    \"type\": \"pie\",\n    \"addTooltip\": true,\n    \"addLegend\": true,\n    \"legendPosition\": \"bottom\",\n    \"isDonut\": true,\n    \"labels\": {\n      \"show\": false,\n      \"values\": true,\n      \"last_level\": true,\n      \"truncate\": 100\n    }\n  },\n  \"aggs\": [\n    {\n      \"id\": \"1\",\n      \"enabled\": true,\n      \"type\": \"count\",\n      \"schema\": \"metric\",\n      \"params\": {}\n    },\n    {\n      \"id\": \"2\",\n      \"enabled\": true,\n      \"type\": \"terms\",\n      \"schema\": \"segment\",\n      \"params\": {\n        \"field\": \"nginx.access.user_agent.name.keyword\",\n        \"size\": 5,\n        \"order\": \"desc\",\n        \"orderBy\": \"1\",\n        \"otherBucket\": false,\n        \"otherBucketLabel\": \"Other\",\n        \"missingBucket\": false,\n        \"missingBucketLabel\": \"Missing\"\n      }\n    },\n    {\n      \"id\": \"3\",\n      \"enabled\": true,\n      \"type\": \"terms\",\n      \"schema\": \"segment\",\n      \"params\": {\n        \"field\": \"nginx.access.user_agent.major.keyword\",\n        \"size\": 5,\n        \"order\": \"desc\",\n        \"orderBy\": \"1\",\n        \"otherBucket\": false,\n        \"otherBucketLabel\": \"Other\",\n        \"missingBucket\": false,\n        \"missingBucketLabel\": \"Missing\"\n      }\n    }\n  ]\n}",
      "uiStateJSON": "{}",
      "description": "",
      "version": 1,
      "kibanaSavedObjectMeta": {
        "searchSourceJSON": "{\n  \"query\": {\n    \"query\": \"\",\n    \"language\": \"kuery\"\n  },\n  \"filter\": [],\n  \"indexRefName\": \"kibanaSavedObjectMeta.searchSourceJSON.index\"\n}"
      }
    },
    "_migrationVersion": {
      "visualization": "7.0.0"
    },
    "_references": [
      {
        "name": "kibanaSavedObjectMeta.searchSourceJSON.index",
        "id": "677aef70-8601-11e9-808b-2d2bf6b1f0ee",
        "type": "index-pattern"
      }
    ]
  },
  {
    "_id": "acd51d00-6d80-11e9-99bc-d5ddcc90f43b",
    "_type": "visualization",
    "_source": {
      "title": "Os Device [Filebeat Nginx]",
      "visState": "{\n  \"title\": \"Os Device [Filebeat Nginx]\",\n  \"type\": \"pie\",\n  \"params\": {\n    \"type\": \"pie\",\n    \"addTooltip\": true,\n    \"addLegend\": true,\n    \"legendPosition\": \"right\",\n    \"isDonut\": true,\n    \"labels\": {\n      \"show\": true,\n      \"values\": true,\n      \"last_level\": true,\n      \"truncate\": 100\n    }\n  },\n  \"aggs\": [\n    {\n      \"id\": \"1\",\n      \"enabled\": true,\n      \"type\": \"count\",\n      \"schema\": \"metric\",\n      \"params\": {}\n    },\n    {\n      \"id\": \"5\",\n      \"enabled\": true,\n      \"type\": \"terms\",\n      \"schema\": \"split\",\n      \"params\": {\n        \"field\": \"nginx.access.user_agent.os_name.keyword\",\n        \"size\": 10,\n        \"order\": \"desc\",\n        \"orderBy\": \"1\",\n        \"otherBucket\": false,\n        \"otherBucketLabel\": \"Other\",\n        \"missingBucket\": false,\n        \"missingBucketLabel\": \"Missing\",\n        \"customLabel\": \".\",\n        \"row\": true\n      }\n    },\n    {\n      \"id\": \"3\",\n      \"enabled\": true,\n      \"type\": \"terms\",\n      \"schema\": \"segment\",\n      \"params\": {\n        \"field\": \"nginx.access.user_agent.name.keyword\",\n        \"size\": 10,\n        \"order\": \"desc\",\n        \"orderBy\": \"1\",\n        \"otherBucket\": false,\n        \"otherBucketLabel\": \"Other\",\n        \"missingBucket\": false,\n        \"missingBucketLabel\": \"Missing\"\n      }\n    },\n    {\n      \"id\": \"4\",\n      \"enabled\": true,\n      \"type\": \"terms\",\n      \"schema\": \"segment\",\n      \"params\": {\n        \"field\": \"nginx.access.user_agent.device.keyword\",\n        \"size\": 10,\n        \"order\": \"desc\",\n        \"orderBy\": \"1\",\n        \"otherBucket\": false,\n        \"otherBucketLabel\": \"Other\",\n        \"missingBucket\": false,\n        \"missingBucketLabel\": \"Missing\"\n      }\n    }\n  ]\n}",
      "uiStateJSON": "{}",
      "description": "",
      "version": 1,
      "kibanaSavedObjectMeta": {
        "searchSourceJSON": "{\n  \"query\": {\n    \"query\": \"\",\n    \"language\": \"kuery\"\n  },\n  \"filter\": [],\n  \"indexRefName\": \"kibanaSavedObjectMeta.searchSourceJSON.index\"\n}"
      }
    },
    "_migrationVersion": {
      "visualization": "7.0.0"
    },
    "_references": [
      {
        "name": "kibanaSavedObjectMeta.searchSourceJSON.index",
        "id": "677aef70-8601-11e9-808b-2d2bf6b1f0ee",
        "type": "index-pattern"
      }
    ]
  },
  {
    "_id": "3954dac0-6d7e-11e9-99bc-d5ddcc90f43b",
    "_type": "visualization",
    "_source": {
      "title": "top pages [Filebeat Nginx]",
      "visState": "{\n  \"title\": \"top pages [Filebeat Nginx]\",\n  \"type\": \"horizontal_bar\",\n  \"params\": {\n    \"type\": \"histogram\",\n    \"grid\": {\n      \"categoryLines\": false,\n      \"valueAxis\": null\n    },\n    \"categoryAxes\": [\n      {\n        \"id\": \"CategoryAxis-1\",\n        \"type\": \"category\",\n        \"position\": \"left\",\n        \"show\": true,\n        \"style\": {},\n        \"scale\": {\n          \"type\": \"linear\"\n        },\n        \"labels\": {\n          \"show\": true,\n          \"rotate\": 0,\n          \"filter\": true,\n          \"truncate\": 100\n        },\n        \"title\": {}\n      }\n    ],\n    \"valueAxes\": [\n      {\n        \"id\": \"ValueAxis-1\",\n        \"name\": \"BottomAxis-1\",\n        \"type\": \"value\",\n        \"position\": \"bottom\",\n        \"show\": true,\n        \"style\": {},\n        \"scale\": {\n          \"type\": \"linear\",\n          \"mode\": \"normal\"\n        },\n        \"labels\": {\n          \"show\": true,\n          \"rotate\": 75,\n          \"filter\": true,\n          \"truncate\": 100\n        },\n        \"title\": {\n          \"text\": \"Count\"\n        }\n      }\n    ],\n    \"seriesParams\": [\n      {\n        \"show\": true,\n        \"type\": \"histogram\",\n        \"mode\": \"normal\",\n        \"data\": {\n          \"label\": \"Count\",\n          \"id\": \"1\"\n        },\n        \"valueAxis\": \"ValueAxis-1\",\n        \"drawLinesBetweenPoints\": true,\n        \"showCircles\": true\n      }\n    ],\n    \"addTooltip\": true,\n    \"addLegend\": true,\n    \"legendPosition\": \"top\",\n    \"times\": [],\n    \"addTimeMarker\": false,\n    \"orderBucketsBySum\": true,\n    \"radiusRatio\": 67\n  },\n  \"aggs\": [\n    {\n      \"id\": \"1\",\n      \"enabled\": true,\n      \"type\": \"count\",\n      \"schema\": \"metric\",\n      \"params\": {\n        \"customLabel\": \"\"\n      }\n    },\n    {\n      \"id\": \"2\",\n      \"enabled\": true,\n      \"type\": \"terms\",\n      \"schema\": \"segment\",\n      \"params\": {\n        \"field\": \"nginx.access.url.keyword\",\n        \"size\": 10,\n        \"order\": \"desc\",\n        \"orderBy\": \"1\",\n        \"otherBucket\": true,\n        \"otherBucketLabel\": \"Other\",\n        \"missingBucket\": true,\n        \"missingBucketLabel\": \"Missing\",\n        \"customLabel\": \".\"\n      }\n    }\n  ]\n}",
      "uiStateJSON": "{\n  \"vis\": {\n    \"legendOpen\": true\n  }\n}",
      "description": "",
      "version": 1,
      "kibanaSavedObjectMeta": {
        "searchSourceJSON": "{\n  \"query\": {\n    \"query\": \"\",\n    \"language\": \"kuery\"\n  },\n  \"filter\": [],\n  \"indexRefName\": \"kibanaSavedObjectMeta.searchSourceJSON.index\"\n}"
      }
    },
    "_migrationVersion": {
      "visualization": "7.0.0"
    },
    "_references": [
      {
        "name": "kibanaSavedObjectMeta.searchSourceJSON.index",
        "id": "677aef70-8601-11e9-808b-2d2bf6b1f0ee",
        "type": "index-pattern"
      }
    ]
  },
  {
    "_id": "039bb340-87a5-11e9-bfec-155022556871",
    "_type": "visualization",
    "_source": {
      "title": "Number of different IP at the same time [kheops]",
      "visState": "{\"title\":\"Number of different IP at the same time [kheops]\",\"type\":\"area\",\"params\":{\"type\":\"area\",\"grid\":{\"categoryLines\":false,\"valueAxis\":\"ValueAxis-1\"},\"categoryAxes\":[{\"id\":\"CategoryAxis-1\",\"type\":\"category\",\"position\":\"bottom\",\"show\":true,\"style\":{},\"scale\":{\"type\":\"linear\"},\"labels\":{\"show\":true,\"truncate\":100},\"title\":{}}],\"valueAxes\":[{\"id\":\"ValueAxis-1\",\"name\":\"LeftAxis-1\",\"type\":\"value\",\"position\":\"left\",\"show\":true,\"style\":{},\"scale\":{\"type\":\"linear\",\"mode\":\"normal\"},\"labels\":{\"show\":true,\"rotate\":0,\"filter\":false,\"truncate\":100},\"title\":{\"text\":\".\"}}],\"seriesParams\":[{\"show\":\"true\",\"type\":\"area\",\"mode\":\"stacked\",\"data\":{\"label\":\".\",\"id\":\"1\"},\"drawLinesBetweenPoints\":true,\"showCircles\":true,\"interpolate\":\"linear\",\"valueAxis\":\"ValueAxis-1\"}],\"addTooltip\":true,\"addLegend\":true,\"legendPosition\":\"top\",\"times\":[],\"addTimeMarker\":false},\"aggs\":[{\"id\":\"1\",\"enabled\":true,\"type\":\"cardinality\",\"schema\":\"metric\",\"params\":{\"field\":\"geoip.ip\",\"customLabel\":\".\"}},{\"id\":\"2\",\"enabled\":true,\"type\":\"date_histogram\",\"schema\":\"segment\",\"params\":{\"field\":\"@timestamp\",\"timeRange\":{\"from\":\"now-15m\",\"to\":\"now\"},\"useNormalizedEsInterval\":true,\"interval\":\"auto\",\"time_zone\":\"Europe/Zurich\",\"drop_partials\":false,\"customInterval\":\"2h\",\"min_doc_count\":1,\"extended_bounds\":{}}}]}",
      "uiStateJSON": "{}",
      "description": "",
      "version": 1,
      "kibanaSavedObjectMeta": {
        "searchSourceJSON": "{\"query\":{\"query\":\"\",\"language\":\"kuery\"},\"filter\":[],\"indexRefName\":\"kibanaSavedObjectMeta.searchSourceJSON.index\"}"
      }
    },
    "_migrationVersion": {
      "visualization": "7.0.0"
    },
    "_references": [
      {
        "name": "kibanaSavedObjectMeta.searchSourceJSON.index",
        "type": "index-pattern",
        "id": "677aef70-8601-11e9-808b-2d2bf6b1f0ee"
      }
    ]
  },
  {
    "_id": "f2622b60-8789-11e9-9cdd-a1261b74e3f8",
    "_type": "visualization",
    "_source": {
      "title": "top request [kheops] (not api)",
      "visState": "{\"aggs\":[{\"enabled\":true,\"id\":\"1\",\"params\":{},\"schema\":\"metric\",\"type\":\"count\"},{\"enabled\":true,\"id\":\"2\",\"params\":{\"customLabel\":\".\",\"field\":\"nginx.access.url.keyword\",\"missingBucket\":false,\"missingBucketLabel\":\"Missing\",\"order\":\"desc\",\"orderBy\":\"1\",\"otherBucket\":false,\"otherBucketLabel\":\"Other\",\"size\":15},\"schema\":\"segment\",\"type\":\"terms\"}],\"params\":{\"addLegend\":true,\"addTimeMarker\":false,\"addTooltip\":true,\"categoryAxes\":[{\"id\":\"CategoryAxis-1\",\"labels\":{\"filter\":false,\"rotate\":0,\"show\":true,\"truncate\":200},\"position\":\"left\",\"scale\":{\"type\":\"linear\"},\"show\":true,\"style\":{},\"title\":{},\"type\":\"category\"}],\"grid\":{\"categoryLines\":false},\"legendPosition\":\"top\",\"orderBucketsBySum\":true,\"seriesParams\":[{\"data\":{\"id\":\"1\",\"label\":\"Count\"},\"drawLinesBetweenPoints\":true,\"mode\":\"normal\",\"show\":true,\"showCircles\":true,\"type\":\"histogram\",\"valueAxis\":\"ValueAxis-1\"}],\"times\":[],\"type\":\"histogram\",\"valueAxes\":[{\"id\":\"ValueAxis-1\",\"labels\":{\"filter\":true,\"rotate\":75,\"show\":true,\"truncate\":100},\"name\":\"LeftAxis-1\",\"position\":\"bottom\",\"scale\":{\"mode\":\"normal\",\"type\":\"linear\"},\"show\":true,\"style\":{},\"title\":{\"text\":\"Count\"},\"type\":\"value\"}]},\"title\":\"top request [kheops] (not api)\",\"type\":\"horizontal_bar\"}",
      "uiStateJSON": "{}",
      "description": "",
      "version": 1,
      "kibanaSavedObjectMeta": {
        "searchSourceJSON": "{\"query\":{\"language\":\"kuery\",\"query\":\"\"},\"filter\":[]}"
      },
      "savedSearchRefName": "search_0"
    },
    "_migrationVersion": {
      "visualization": "7.0.0"
    },
    "_references": [
      {
        "name": "search_0",
        "type": "search",
        "id": "9fd4e630-8789-11e9-9cdd-a1261b74e3f8"
      }
    ]
  },
  {
    "_id": "1cfb1a80-a1f4-11e7-928f-5dbe6f6f5519",
    "_type": "visualization",
    "_source": {
      "title": "Access logs over time [Filebeat Nginx]",
      "visState": "{\"title\":\"Access logs over time [Filebeat Nginx]\",\"type\":\"metrics\",\"params\":{\"background_color_rules\":[{\"id\":\"3189aa80-a1f3-11e7-a062-a1c3587f4874\"}],\"index_pattern\":\"kheopsnginx-*\",\"time_field\":\"@timestamp\",\"series\":[{\"line_width\":1,\"terms_field\":\"nginx.access.url\",\"point_size\":1,\"split_filters\":[{\"color\":\"#68BC00\",\"id\":\"1db649a0-a1f3-11e7-a062-a1c3587f4874\"}],\"color\":\"#68BC00\",\"label\":\"Access logs\",\"metrics\":[{\"type\":\"count\",\"id\":\"61ca57f2-469d-11e7-af02-69e470af7417\"}],\"seperate_axis\":0,\"split_mode\":\"everything\",\"chart_type\":\"line\",\"terms_order_by\":\"61ca57f2-469d-11e7-af02-69e470af7417\",\"stacked\":\"none\",\"axis_position\":\"right\",\"formatter\":\"number\",\"id\":\"61ca57f1-469d-11e7-af02-69e470af7417\",\"fill\":0.5}],\"axis_formatter\":\"number\",\"interval\":\"auto\",\"id\":\"61ca57f0-469d-11e7-af02-69e470af7417\",\"filter\":\"nginx.log_type:access\",\"show_legend\":1,\"show_grid\":1,\"legend_position\":\"bottom\",\"axis_position\":\"left\",\"type\":\"timeseries\",\"annotations\":[{\"fields\":\"\",\"template\":\"\",\"index_pattern\":\"kheopsnginx-*\",\"query_string\":\"\",\"id\":\"e38af7a0-6b4d-11e9-bde5-fdf1343b568d\",\"color\":\"#F00\",\"time_field\":\"@timestamp\",\"ignore_global_filters\":0,\"ignore_panel_filters\":0}],\"axis_scale\":\"normal\",\"default_index_pattern\":\"kheopsnginx-*\"},\"aggs\":[]}",
      "uiStateJSON": "{}",
      "description": "",
      "version": 1,
      "kibanaSavedObjectMeta": {
        "searchSourceJSON": "{\"query\":{\"query\":\"\",\"language\":\"kuery\"},\"filter\":[]}"
      }
    },
    "_migrationVersion": {
      "visualization": "7.0.0"
    },
    "_references": []
  },
  {
    "_id": "e3024c30-8613-11e9-814b-db905ea394b7",
    "_type": "visualization",
    "_source": {
      "title": "Error logs over time [Filebeat Nginx]",
      "visState": "{\"title\":\"Error logs over time [Filebeat Nginx]\",\"type\":\"metrics\",\"params\":{\"background_color_rules\":[{\"id\":\"3189aa80-a1f3-11e7-a062-a1c3587f4874\"}],\"index_pattern\":\"kheopsnginx-*\",\"time_field\":\"@timestamp\",\"series\":[{\"line_width\":1,\"terms_field\":\"nginx.access.url\",\"point_size\":1,\"split_filters\":[{\"color\":\"#68BC00\",\"id\":\"1db649a0-a1f3-11e7-a062-a1c3587f4874\"}],\"color\":\"rgba(188,0,3,1)\",\"label\":\"Access logs\",\"metrics\":[{\"type\":\"count\",\"id\":\"61ca57f2-469d-11e7-af02-69e470af7417\"}],\"seperate_axis\":0,\"split_mode\":\"everything\",\"chart_type\":\"line\",\"terms_order_by\":\"61ca57f2-469d-11e7-af02-69e470af7417\",\"stacked\":\"none\",\"axis_position\":\"right\",\"formatter\":\"number\",\"id\":\"61ca57f1-469d-11e7-af02-69e470af7417\",\"fill\":0.5}],\"axis_formatter\":\"number\",\"interval\":\"auto\",\"id\":\"61ca57f0-469d-11e7-af02-69e470af7417\",\"filter\":\"nginx.log_type:error\",\"show_legend\":1,\"show_grid\":1,\"legend_position\":\"bottom\",\"axis_position\":\"left\",\"type\":\"timeseries\",\"annotations\":[{\"fields\":\"\",\"template\":\"\",\"index_pattern\":\"kheopsnginx-*\",\"query_string\":\"\",\"id\":\"e38af7a0-6b4d-11e9-bde5-fdf1343b568d\",\"color\":\"#F00\",\"time_field\":\"@timestamp\",\"ignore_global_filters\":0,\"ignore_panel_filters\":0}],\"axis_scale\":\"normal\",\"default_index_pattern\":\"kheopsnginx-*\"},\"aggs\":[]}",
      "uiStateJSON": "{}",
      "description": "",
      "version": 1,
      "kibanaSavedObjectMeta": {
        "searchSourceJSON": "{\"query\":{\"query\":\"\",\"language\":\"kuery\"},\"filter\":[]}"
      }
    },
    "_migrationVersion": {
      "visualization": "7.0.0"
    },
    "_references": []
  }
]